tesseract_olap/__init__.py
tesseract_olap/__main__.py
tesseract_olap/backend/__init__.py
tesseract_olap/backend/cache.py
tesseract_olap/backend/clickhouse/__init__.py
tesseract_olap/backend/clickhouse/backend_http.py
tesseract_olap/backend/clickhouse/backend_native.py
tesseract_olap/backend/clickhouse/cursor.py
tesseract_olap/backend/clickhouse/debug.py
tesseract_olap/backend/clickhouse/dialect.py
tesseract_olap/backend/clickhouse/sql_common.py
tesseract_olap/backend/clickhouse/sql_data.py
tesseract_olap/backend/clickhouse/sql_members.py
tesseract_olap/backend/clickhouse/time.py
tesseract_olap/backend/dataframe.py
tesseract_olap/backend/models.py
tesseract_olap/backend/sqlite.py
tesseract_olap/backend/valkey.py
tesseract_olap/common/__init__.py
tesseract_olap/common/strings.py
tesseract_olap/common/types.py
tesseract_olap/common/url.py
tesseract_olap/exceptions/__init__.py
tesseract_olap/exceptions/backend.py
tesseract_olap/exceptions/query.py
tesseract_olap/exceptions/schema.py
tesseract_olap/exceptions/server.py
tesseract_olap/logiclayer/__init__.py
tesseract_olap/logiclayer/debug.py
tesseract_olap/logiclayer/dependencies.py
tesseract_olap/logiclayer/module.py
tesseract_olap/logiclayer/response.py
tesseract_olap/query/__init__.py
tesseract_olap/query/enums.py
tesseract_olap/query/models.py
tesseract_olap/query/queries.py
tesseract_olap/query/requests.py
tesseract_olap/schema/__init__.py
tesseract_olap/schema/aggregators.py
tesseract_olap/schema/csv.py
tesseract_olap/schema/enums.py
tesseract_olap/schema/formulas.py
tesseract_olap/schema/json.py
tesseract_olap/schema/models.py
tesseract_olap/schema/public.py
tesseract_olap/schema/schema.xsd
tesseract_olap/schema/traverse.py
tesseract_olap/schema/validator.py
tesseract_olap/schema/xml.py
tesseract_olap/server/__init__.py
tesseract_olap/server/schema.py
tesseract_olap/server/server.py
tesseract_olap-0.22.5.dist-info/METADATA
tesseract_olap-0.22.5.dist-info/WHEEL
tesseract_olap-0.22.5.dist-info/entry_points.txt
tesseract_olap-0.22.5.dist-info/RECORD
