Metadata-Version: 2.4
Name: tesseract-olap
Version: 0.22.5
Summary: A semantic layer for your data.
License: Proprietary
Author: Francisco Abarzua
Author-email: francisco@datawheel.us
Maintainer: Francisco Abarzua
Maintainer-email: francisco@datawheel.us
Requires-Python: >=3.9, <4.0
Classifier: License :: Other/Proprietary License
Classifier: Programming Language :: Python :: 3
Classifier: Programming Language :: Python :: 3.9
Classifier: Programming Language :: Python :: 3.10
Classifier: Programming Language :: Python :: 3.11
Classifier: Programming Language :: Python :: 3.12
Classifier: Programming Language :: Python :: 3.13
Classifier: Programming Language :: Python :: 3.14
Classifier: Topic :: Software Development :: Libraries :: Python Modules
Provides-Extra: clickhouse
Provides-Extra: redis
Requires-Dist: PyPika (>=0.48.0,<0.49.0)
Requires-Dist: clickhouse-cityhash (>=1.0.2.4) ; extra == "clickhouse"
Requires-Dist: clickhouse-connect (>=0.8.16) ; extra == "clickhouse"
Requires-Dist: clickhouse-driver[lz4] (>=0.2.0) ; extra == "clickhouse"
Requires-Dist: fnv-c (>=0.2,<1.0)
Requires-Dist: httpx (>=0.18,<1.0)
Requires-Dist: immutables (>=0.16,<1.0)
Requires-Dist: lfudacache (==0.0.2)
Requires-Dist: lxml (>=4.6)
Requires-Dist: orjson (>=3.8,<4.0)
Requires-Dist: polars (>=1.24,<2.0)
Requires-Dist: pydantic (>=2.11,<3.0)
Requires-Dist: pyparsing (==3.2.3)
Requires-Dist: python-dateutil (>=2.9.0.post0,<3.0)
Requires-Dist: redis (>=5.0,<6.0) ; extra == "redis"
Requires-Dist: strenum (>=0.4,<1.0)
Requires-Dist: typing-extensions (>=4.5)
Requires-Dist: xlsxwriter (>=3.2,<4.0)
Requires-Dist: xmlschema (>=3.3,<4.0)
Project-URL: Repository, https://github.com/Datawheel/tesseract-olap
